peano/__init__.py
peano/peano.py
peano-0.1.3.dist-info/LICENSE
peano-0.1.3.dist-info/WHEEL
peano-0.1.3.dist-info/METADATA
peano-0.1.3.dist-info/RECORD
